gridsource/__init__.py
gridsource/autodoc.py
gridsource/cli.py
gridsource/custom_systems.txt
gridsource/io.py
gridsource/utils.py
gridsource/validation.py
gridsource-2.3.2.dist-info/AUTHORS.rst
gridsource-2.3.2.dist-info/LICENSE
gridsource-2.3.2.dist-info/METADATA
gridsource-2.3.2.dist-info/WHEEL
gridsource-2.3.2.dist-info/entry_points.txt
gridsource-2.3.2.dist-info/RECORD
