Metadata-Version: 2.1
Name: gridsource
Version: 2.3.2
Summary: Data mining with XLSX, cfg, json, etc.
Author: Nicolas Cordier
Author-email: nicolas.cordier@numeric-gmbh.ch
Requires-Python: >3.10
Classifier: Programming Language :: Python :: 3
Classifier: Programming Language :: Python :: 3.11
Classifier: Programming Language :: Python :: 3.12
Requires-Dist: Click
Requires-Dist: PyYAML
Requires-Dist: configobj
Requires-Dist: jsonschema
Requires-Dist: openpyxl
Requires-Dist: pint (>=0.17)
Requires-Dist: pint-pandas (>=0.2)
Requires-Dist: simplejson
Requires-Dist: tabulate (>=0.9.0,<0.10.0)
Requires-Dist: xlrd
Requires-Dist: xlsxwriter
Requires-Dist: zipp
